LICENSE
MANIFEST.in
README.rst
setup.cfg
setup.py
properties/__init__.py
properties/base.py
properties/basic.py
properties/handlers.py
properties/images.py
properties/math.py
properties/utils.py
properties.egg-info/PKG-INFO
properties.egg-info/SOURCES.txt
properties.egg-info/dependency_links.txt
properties.egg-info/requires.txt
properties.egg-info/top_level.txt
properties/task/__init__.py
properties/task/base.py
properties/task/image.py