Metadata-Version: 1.1
Name: properties
Version: 0.3.0
Summary: properties
Home-page: http://steno3d.com/
Author: 3point Science
Author-email: info@3ptscience.com
License: UNKNOWN
Download-URL: http://github.com/3ptscience/properties
Keywords: property
Platform: Windows
Platform: Linux
Platform: Solaris
Platform: Mac OS-X
Platform: Unix
Classifier: Development Status :: 4 - Beta
Classifier: Programming Language :: Python
Classifier: Topic :: Scientific/Engineering
Classifier: Topic :: Scientific/Engineering :: Mathematics
Classifier: Topic :: Scientific/Engineering :: Physics
Classifier: Operating System :: Microsoft :: Windows
Classifier: Operating System :: POSIX
Classifier: Operating System :: Unix
Classifier: Operating System :: MacOS
Classifier: Natural Language :: English
